containerl/__init__.py
containerl/cli.py
containerl/py.typed
containerl/interface/__init__.py
containerl/interface/proto_pb2.py
containerl/interface/proto_pb2.pyi
containerl/interface/proto_pb2_grpc.py
containerl/interface/proto_pb2_grpc.pyi
containerl/interface/utils.py
containerl/interface/agent/__init__.py
containerl/interface/agent/client.py
containerl/interface/agent/server_factory.py
containerl/interface/environment/__init__.py
containerl/interface/environment/client.py
containerl/interface/environment/client_vec.py
containerl/interface/environment/server_factory.py
containerl/interface/environment/server_factory_vec.py
containerl/scripts/__init__.py
containerl/scripts/containerl_cli.py
containerl-0.1.3.dist-info/licenses/LICENSE
containerl-0.1.3.dist-info/METADATA
containerl-0.1.3.dist-info/WHEEL
containerl-0.1.3.dist-info/entry_points.txt
containerl-0.1.3.dist-info/top_level.txt
containerl-0.1.3.dist-info/RECORD
