Metadata-Version: 2.4
Name: containerl
Version: 0.1.3
Summary: Toolkit to package and deploy reinforcement learning environments and agents inside reproducible containers
Author-email: Alessandro Palmas <alex@artificialtwin.com>
Maintainer-email: Alessandro Palmas <alex@artificialtwin.com>
License: MIT License
Project-URL: Homepage, https://github.com/alexpalms/containerl
Project-URL: Issues, https://github.com/alexpalms/containerl/issues
Keywords: reinforcement-learning,containers,docker,gymnasium,grpc,rl,machine-learning
Classifier: Development Status :: 3 - Alpha
Classifier: Intended Audience :: Developers
Classifier: Intended Audience :: Science/Research
Classifier: License :: OSI Approved :: MIT License
Classifier: Operating System :: POSIX :: Linux
Classifier: Programming Language :: Python :: 3
Classifier: Programming Language :: Python :: 3.12
Classifier: Programming Language :: Python :: 3 :: Only
Classifier: Topic :: Scientific/Engineering :: Artificial Intelligence
Classifier: Topic :: Software Development :: Libraries :: Python Modules
Requires-Python: >=3.12
License-File: LICENSE
Requires-Dist: gymnasium
Requires-Dist: grpcio-tools
Requires-Dist: msgpack
Dynamic: license-file
